{
  "hash": "25fca0acc89e14795e92dc40660f7fa2",
  "result": {
    "engine": "jupyter",
    "markdown": "---\ntitle: \"homework4\"\nauthor: \"강남규\"\ndate: \"2024-07-25\"\ncategories: [bigdata]\n---\n\n# 패키지 불러오기\n\n::: {#b7284e53 .cell execution_count=1}\n``` {.python .cell-code}\nimport pandas as pd\nimport numpy as np\nimport math\n!pip install scipy\nfrom scipy.stats import norm\nimport seaborn as sns\nimport matplotlib.pyplot as plt\n```\n\n::: {.cell-output .cell-output-stdout}\n```\nDefaulting to user installation because normal site-packages is not writeable\nRequirement already satisfied: scipy in c:\\users\\user\\appdata\\roaming\\python\\python312\\site-packages (1.14.0)\nRequirement already satisfied: numpy<2.3,>=1.23.5 in c:\\users\\user\\appdata\\roaming\\python\\python312\\site-packages (from scipy) (2.0.1)\n```\n:::\n:::\n\n\n# Q1\n\n정규분포 pdf 값을 계산하는 자신만의 파이썬 함수를 정의하고,정규분포 mu = 3, sigma = 2 의 pdf를 그릴 것.\n\n::: {#62c9c2ba .cell execution_count=2}\n``` {.python .cell-code}\ndef normal(x, mu, sigma):\n    a = 1 / (sigma * math.sqrt(2 * math.pi))\n    b = (x - mu) / sigma\n    return a * math.exp(-0.5 * b ** 2)\n\nk = np.linspace(-2, 8, 100)\np = []\nfor i in k:\n  p.append(normal(i, 3, 2))\n\nplt.plot(k,p)\nplt.show()\nplt.clf()  \n```\n\n::: {.cell-output .cell-output-display}\n![](hw4_files/figure-html/cell-3-output-1.png){width=587 height=411}\n:::\n\n::: {.cell-output .cell-output-display}\n```\n<Figure size 672x480 with 0 Axes>\n```\n:::\n:::\n\n\n# Q2\n\n- 파이썬 scipy 패키지 사용해서 다음과 같은 확률을 구하시오\n- X ~ N(2, 3^2)\n\n\n## 1. P(X < 3)\n\n::: {#d6e4867e .cell execution_count=3}\n``` {.python .cell-code}\na1 = norm.cdf(3, 2, 3)\n\nprint('확률은 ' + str(a1.round(2)) + '입니다')\n```\n\n::: {.cell-output .cell-output-stdout}\n```\n확률은 0.63입니다\n```\n:::\n:::\n\n\n## 2. P(2 < X < 5)\n\n::: {#fb84aad4 .cell execution_count=4}\n``` {.python .cell-code}\na2 = norm.cdf(5, 2, 3) - norm.cdf(2, 2, 3)\n\nprint('확률은 ' + str(a2.round(2)) + '입니다')\n```\n\n::: {.cell-output .cell-output-stdout}\n```\n확률은 0.34입니다\n```\n:::\n:::\n\n\n## 3. P(X < 3 or X > 7)\n\n::: {#146eddb9 .cell execution_count=5}\n``` {.python .cell-code}\na3 = norm.cdf(3, 2, 3) + (1 - norm.cdf(7, 2, 3))\n\nprint('확률은 ' + str(a3.round(2)) + '입니다')\n```\n\n::: {.cell-output .cell-output-stdout}\n```\n확률은 0.68입니다\n```\n:::\n:::\n\n\n# Q3\n\nLS 빅데이터 스쿨 학생들의 중간고사 점수는 평균이 30이고, 분산이 4인 정규분포를 따른다.\n상위 5%에 해당하는 학생의 점수는?\n\n::: {#5d46ee41 .cell execution_count=6}\n``` {.python .cell-code}\na4 = norm.ppf(0.95, 30, 2)\n\nprint('해당 학생의 점수는 ' + str(a4.round(2)) + '입니다')\n```\n\n::: {.cell-output .cell-output-stdout}\n```\n해당 학생의 점수는 33.29입니다\n```\n:::\n:::\n\n\n",
    "supporting": [
      "hw4_files"
    ],
    "filters": [],
    "includes": {}
  }
}